setup.py
Flask_Slither.egg-info/PKG-INFO
Flask_Slither.egg-info/SOURCES.txt
Flask_Slither.egg-info/dependency_links.txt
Flask_Slither.egg-info/not-zip-safe
Flask_Slither.egg-info/requires.txt
Flask_Slither.egg-info/top_level.txt
flask_slither/__init__.py
flask_slither/db.py
flask_slither/decorators.py
flask_slither/resources.py