Metadata-Version: 1.1
Name: Flask-Slither
Version: 1.1.3
Summary: A small library between MongoDB and JSON API endpoints
Home-page: http://github.com/gevious/flask_slither
Author: Nico Gevers
Author-email: me@gevious.com
License: MIT
Platform: any
Classifier: Environment :: Web Environment
Classifier: Intended Audience :: Developers
Classifier: License :: OSI Approved :: MIT License
Classifier: Operating System :: OS Independent
Classifier: Programming Language :: Python
Classifier: Topic :: Internet :: WWW/HTTP :: Dynamic Content
Classifier: Topic :: Software Development :: Libraries :: Python Modules
